django_qr/__init__.py
django_qr/apps.py
django_qr/conf.py
django_qr/main.py
django_qr/migrations/0001_initial.py
django_qr/migrations/__init__.py
django_qr/models.py
django_qr/py.typed
django_qr/urls.py
django_qr/views.py
django_qr-0.2.0.dist-info/LICENSE
django_qr-0.2.0.dist-info/METADATA
django_qr-0.2.0.dist-info/WHEEL
django_qr-0.2.0.dist-info/RECORD
