Metadata-Version: 2.1
Name: django-qr
Version: 0.2.0
Summary: Generate and manage QR codes that redirect to specific views in your Django project
Home-page: https://github.com/abe-101/django-qr
License: MIT
Author: Abe Hanoka
Author-email: abe@habet.dev
Requires-Python: >=3.8,<4.0
Classifier: Development Status :: 2 - Pre-Alpha
Classifier: Framework :: Django
Classifier: Framework :: Django :: 4.2
Classifier: Framework :: Django :: 5.0
Classifier: Framework :: Django :: 5.1
Classifier: Intended Audience :: Developers
Classifier: License :: OSI Approved :: MIT License
Classifier: Natural Language :: English
Classifier: Operating System :: OS Independent
Classifier: Programming Language :: Python :: 3
Classifier: Programming Language :: Python :: 3.8
Classifier: Programming Language :: Python :: 3.9
Classifier: Programming Language :: Python :: 3.10
Classifier: Programming Language :: Python :: 3.11
Classifier: Programming Language :: Python :: 3.12
Classifier: Programming Language :: Python :: 3.13
Classifier: Topic :: Software Development :: Libraries
Requires-Dist: django (>=4.2)
Requires-Dist: segno (>=1.6.1,<2.0.0)
Project-URL: Bug Tracker, https://github.com/abe-101/django-qr/issues
Project-URL: Changelog, https://github.com/abe-101/django-qr/blob/main/CHANGELOG.md
Project-URL: Documentation, https://django-qr.readthedocs.io
Project-URL: Repository, https://github.com/abe-101/django-qr
